[
    {
        "date": "2019-12-09",
        "package": "@ionic/angular@4.11.5",
        "audits": {
            "first-contentful-paint": 1826.1970000000001,
            "first-meaningful-paint": 1826.1970000000001,
            "load-fast-enough-for-pwa": 2271.8810000000003,
            "speed-index": 1826.1970000000001,
            "estimated-input-latency": 12.8,
            "total-blocking-time": 38.5,
            "max-potential-fid": 88.5,
            "time-to-first-byte": 9.105,
            "first-cpu-idle": 2041.0259999999998,
            "interactive": 2271.8810000000003,
            "mainthread-work-breakdown": 583.748,
            "bootup-time": 360.1,
            "network-requests": 12,
            "network-rtt": 0.05099999999999999,
            "network-server-latency": 2.342,
            "main-thread-tasks": 6,
            "metrics": 2271.8810000000003,
            "total-byte-weight": 144889,
            "render-blocking-resources": 152,
            "dom-size": 31
        },
        "time": 1575871896317
    },
    {
        "date": "2019-12-09",
        "package": "@ionic/angular@4.11.5",
        "audits": {
            "first-contentful-paint": 1835.0814999999998,
            "first-meaningful-paint": 1835.0814999999998,
            "load-fast-enough-for-pwa": 2120.545,
            "speed-index": 1835.0814999999998,
            "estimated-input-latency": 12.8,
            "total-blocking-time": 34.000000000000114,
            "max-potential-fid": 84.00000000000011,
            "time-to-first-byte": 10.129999999999999,
            "first-cpu-idle": 1835.0814999999998,
            "interactive": 2120.545,
            "mainthread-work-breakdown": 618.5520000000001,
            "bootup-time": 359.464,
            "network-requests": 12,
            "network-rtt": 0.07100000000000001,
            "network-server-latency": 2.3089999999999997,
            "main-thread-tasks": 6,
            "metrics": 2120.545,
            "total-byte-weight": 144889,
            "render-blocking-resources": 152,
            "dom-size": 31
        },
        "time": 1575872325827
    },
    {
        "date": "2019-12-09",
        "package": "@ionic/angular@4.11.5",
        "audits": {
            "first-contentful-paint": 1830.2755000000002,
            "first-meaningful-paint": 1830.2755000000002,
            "load-fast-enough-for-pwa": 2285.8615,
            "speed-index": 1830.2755000000002,
            "estimated-input-latency": 12.8,
            "total-blocking-time": 50,
            "max-potential-fid": 101,
            "time-to-first-byte": 9.636000000000001,
            "first-cpu-idle": 2056.379,
            "interactive": 2285.8615,
            "mainthread-work-breakdown": 615.94,
            "bootup-time": 381.17600000000033,
            "network-requests": 12,
            "network-rtt": 0.04299999999999998,
            "network-server-latency": 1.7930000000000001,
            "main-thread-tasks": 7,
            "metrics": 2285.8615,
            "total-byte-weight": 144889,
            "render-blocking-resources": 152,
            "dom-size": 31
        },
        "time": 1575872762986
    },
    {
        "date": "2019-12-09",
        "package": "@ionic/angular@4.11.5",
        "audits": {
            "first-contentful-paint": 2013.3575,
            "first-meaningful-paint": 2013.3575,
            "load-fast-enough-for-pwa": 2275.8475,
            "speed-index": 2013.3575,
            "estimated-input-latency": 12.8,
            "total-blocking-time": 130,
            "max-potential-fid": 180,
            "time-to-first-byte": 18.445,
            "first-cpu-idle": 2042.7350000000001,
            "interactive": 2275.8475,
            "mainthread-work-breakdown": 766.7160000000002,
            "bootup-time": 530.4160000000003,
            "network-requests": 12,
            "network-rtt": 0.06399999999999995,
            "network-server-latency": 3.2449999999999997,
            "main-thread-tasks": 8,
            "metrics": 2275.8475,
            "total-byte-weight": 144889,
            "render-blocking-resources": 153,
            "dom-size": 31
        },
        "time": 1575873212969
    }
]