[
    {
        "date": "2019-12-09",
        "datetime": "2019-12-09T13:51:42.788Z",
        "package": "@ionic/angular@4.11.5",
        "audits": {
            "first-contentful-paint": 2812.722,
            "first-meaningful-paint": 2812.722,
            "load-fast-enough-for-pwa": 2812.722,
            "speed-index": 2813,
            "estimated-input-latency": 16,
            "max-potential-fid": 16,
            "time-to-first-byte": 563.3679999999999,
            "first-cpu-idle": 2812.722,
            "interactive": 2812.722,
            "mainthread-work-breakdown": 574.5689999999998,
            "bootup-time": 336.03199999999987,
            "network-requests": 12,
            "network-rtt": 0.08499999999999999,
            "network-server-latency": 572.259,
            "main-thread-tasks": 13,
            "metrics": 2812.722,
            "total-byte-weight": 144889,
            "render-blocking-resources": 722,
            "dom-size": 31
        },
        "time": 1575899502788
    },
    {
        "date": "2019-12-09",
        "datetime": "2019-12-09T14:03:51.202Z",
        "package": "@ionic/angular@4.11.5",
        "audits": {
            "first-contentful-paint": 3020.07,
            "first-meaningful-paint": 3020.07,
            "load-fast-enough-for-pwa": 3020.07,
            "speed-index": 3029,
            "estimated-input-latency": 16,
            "max-potential-fid": 16,
            "time-to-first-byte": 563.562,
            "first-cpu-idle": 3020.07,
            "interactive": 3020.07,
            "mainthread-work-breakdown": 810.243,
            "bootup-time": 602.3169999999999,
            "network-requests": 12,
            "network-rtt": 0.09100000000000001,
            "network-server-latency": 572.1289999999999,
            "main-thread-tasks": 14,
            "metrics": 3020.07,
            "total-byte-weight": 144889,
            "render-blocking-resources": 722,
            "dom-size": 31
        },
        "time": 1575900231202
    },
    {
        "date": "2019-12-09",
        "datetime": "2019-12-09T14:11:36.597Z",
        "package": "@ionic/angular@4.11.5",
        "audits": {
            "first-contentful-paint": 2873.738,
            "first-meaningful-paint": 2873.738,
            "load-fast-enough-for-pwa": 2873.738,
            "speed-index": 2880,
            "estimated-input-latency": 16,
            "max-potential-fid": 16,
            "time-to-first-byte": 565.431,
            "first-cpu-idle": 2873.738,
            "interactive": 2873.738,
            "mainthread-work-breakdown": 669.6999999999991,
            "bootup-time": 433.4179999999996,
            "network-requests": 12,
            "network-rtt": 0.08,
            "network-server-latency": 570.4739999999999,
            "main-thread-tasks": 15,
            "metrics": 2873.738,
            "total-byte-weight": 144889,
            "render-blocking-resources": 720,
            "dom-size": 31
        },
        "time": 1575900696597
    },
    {
        "date": "2019-12-09",
        "datetime": "2019-12-09T15:34:11.409Z",
        "package": "@ionic/angular@4.11.5",
        "audits": {
            "scriptEvaluation": 567.827999999999,
            "other": 130.49900000000005,
            "scriptParseCompile": 88.48200000000003,
            "styleLayout": 35.781,
            "parseHTML": 11.507999999999997,
            "paintCompositeRender": 7.3629999999999995,
            "first-contentful-paint": 3022.571,
            "first-meaningful-paint": 3022.571,
            "load-fast-enough-for-pwa": 3022.571,
            "speed-index": 3030,
            "estimated-input-latency": 16,
            "max-potential-fid": 16,
            "time-to-first-byte": 565.9440000000001,
            "first-cpu-idle": 3022.571,
            "interactive": 3022.571,
            "mainthread-work-breakdown": 841.4609999999991,
            "bootup-time": 621.0189999999996,
            "network-requests": 12,
            "network-rtt": 0.091,
            "network-server-latency": 570.5400000000001,
            "main-thread-tasks": 16,
            "metrics": 3022.571,
            "total-byte-weight": 144889,
            "render-blocking-resources": 721,
            "dom-size": 31
        },
        "time": 1575905651409
    },
    {
        "date": "2019-12-09",
        "datetime": "2019-12-09T15:42:34.080Z",
        "package": "@ionic/angular@4.11.5",
        "audits": {
            "scriptEvaluation": 429.49099999999993,
            "other": 100.22199999999994,
            "scriptParseCompile": 60.54300000000001,
            "styleLayout": 37.608000000000004,
            "parseHTML": 10.906,
            "paintCompositeRender": 7.728,
            "first-contentful-paint": 2882.609,
            "first-meaningful-paint": 2882.609,
            "load-fast-enough-for-pwa": 2882.609,
            "speed-index": 2895,
            "estimated-input-latency": 16,
            "max-potential-fid": 16,
            "time-to-first-byte": 564.4490000000001,
            "first-cpu-idle": 2882.609,
            "interactive": 2882.609,
            "mainthread-work-breakdown": 646.4979999999998,
            "bootup-time": 367.67099999999976,
            "network-requests": 12,
            "network-rtt": 0.063,
            "network-server-latency": 572.0110000000001,
            "main-thread-tasks": 13,
            "metrics": 2882.609,
            "total-byte-weight": 144889,
            "render-blocking-resources": 722,
            "dom-size": 31
        },
        "time": 1575906154080
    },
    {
        "date": "2019-12-09",
        "datetime": "2019-12-09T17:35:45.869Z",
        "package": "@ionic/angular@4.11.5",
        "audits": {
            "scriptEvaluation": 421.09399999999954,
            "other": 102.59299999999993,
            "scriptParseCompile": 55.64999999999998,
            "styleLayout": 39.173,
            "parseHTML": 13.027,
            "paintCompositeRender": 5.58,
            "garbageCollection": 3.097,
            "first-contentful-paint": 2853.326,
            "first-meaningful-paint": 2853.326,
            "load-fast-enough-for-pwa": 2853.326,
            "speed-index": 2866,
            "estimated-input-latency": 16,
            "max-potential-fid": 16,
            "time-to-first-byte": 565.998,
            "first-cpu-idle": 2853.326,
            "interactive": 2853.326,
            "mainthread-work-breakdown": 640.2139999999995,
            "bootup-time": 361.0979999999999,
            "network-requests": 12,
            "network-rtt": 0.086,
            "network-server-latency": 569.616,
            "main-thread-tasks": 14,
            "metrics": 2853.326,
            "total-byte-weight": 144889,
            "render-blocking-resources": 720,
            "dom-size": 31
        },
        "time": 1575912945869
    },
    {
        "date": "2019-12-09",
        "datetime": "2019-12-09T17:43:42.722Z",
        "package": "@ionic/angular@4.11.5",
        "audits": {
            "scriptEvaluation": 483.8989999999993,
            "other": 134.86899999999991,
            "styleLayout": 60.568,
            "scriptParseCompile": 55.631000000000014,
            "parseHTML": 20.779999999999998,
            "paintCompositeRender": 5.2570000000000014,
            "garbageCollection": 2.91,
            "first-contentful-paint": 2951.488,
            "first-meaningful-paint": 2951.488,
            "load-fast-enough-for-pwa": 2951.488,
            "speed-index": 2965,
            "estimated-input-latency": 16,
            "max-potential-fid": 16,
            "time-to-first-byte": 566.616,
            "first-cpu-idle": 2951.488,
            "interactive": 2951.488,
            "mainthread-work-breakdown": 763.9139999999991,
            "bootup-time": 470.24299999999965,
            "network-requests": 12,
            "network-rtt": 0.121,
            "network-server-latency": 571.2869999999999,
            "main-thread-tasks": 17,
            "metrics": 2951.488,
            "total-byte-weight": 144889,
            "render-blocking-resources": 721,
            "dom-size": 31
        },
        "time": 1575913422722
    },
    {
        "date": "2019-12-09",
        "datetime": "2019-12-09T17:51:27.561Z",
        "package": "@ionic/angular@4.11.5",
        "audits": {
            "scriptEvaluation": 500.35799999999944,
            "other": 122.98400000000004,
            "scriptParseCompile": 79.018,
            "styleLayout": 34.574,
            "parseHTML": 12.842999999999998,
            "paintCompositeRender": 6.871999999999999,
            "first-contentful-paint": 2955.596,
            "first-meaningful-paint": 2955.596,
            "load-fast-enough-for-pwa": 2955.596,
            "speed-index": 2961,
            "estimated-input-latency": 16,
            "max-potential-fid": 16,
            "time-to-first-byte": 563.64,
            "first-cpu-idle": 2955.596,
            "interactive": 2955.596,
            "mainthread-work-breakdown": 756.6489999999993,
            "bootup-time": 548.8879999999998,
            "network-requests": 12,
            "network-rtt": 0.13,
            "network-server-latency": 569.828,
            "main-thread-tasks": 15,
            "metrics": 2955.596,
            "total-byte-weight": 144889,
            "render-blocking-resources": 720,
            "dom-size": 31
        },
        "time": 1575913887561
    },
    {
        "date": "2019-12-09",
        "datetime": "2019-12-09T17:59:48.761Z",
        "package": "@ionic/angular@4.11.5",
        "audits": {
            "scriptEvaluation": 510.0289999999997,
            "other": 114.44000000000004,
            "scriptParseCompile": 71.05700000000002,
            "styleLayout": 29.795,
            "parseHTML": 13.027,
            "paintCompositeRender": 8.997999999999998,
            "first-contentful-paint": 2942.313,
            "first-meaningful-paint": 2942.313,
            "load-fast-enough-for-pwa": 2942.313,
            "speed-index": 2954,
            "estimated-input-latency": 16,
            "max-potential-fid": 16,
            "time-to-first-byte": 568.651,
            "first-cpu-idle": 2942.313,
            "interactive": 2942.313,
            "mainthread-work-breakdown": 747.3459999999998,
            "bootup-time": 552.4429999999999,
            "network-requests": 12,
            "network-rtt": 0.087,
            "network-server-latency": 573.1510000000001,
            "main-thread-tasks": 15,
            "metrics": 2942.313,
            "total-byte-weight": 144889,
            "render-blocking-resources": 723,
            "dom-size": 31
        },
        "time": 1575914388761
    },
    {
        "date": "2019-12-09",
        "datetime": "2019-12-09T18:09:26.397Z",
        "package": "@ionic/angular@4.11.5",
        "audits": {
            "scriptEvaluation": 505.9979999999997,
            "other": 106.50599999999999,
            "scriptParseCompile": 69.451,
            "styleLayout": 27.829,
            "parseHTML": 8.417000000000002,
            "paintCompositeRender": 8.351999999999995,
            "first-contentful-paint": 2903.699,
            "first-meaningful-paint": 2903.699,
            "load-fast-enough-for-pwa": 2903.699,
            "speed-index": 2904,
            "estimated-input-latency": 16,
            "max-potential-fid": 16,
            "time-to-first-byte": 569.1800000000001,
            "first-cpu-idle": 2903.699,
            "interactive": 2903.699,
            "mainthread-work-breakdown": 726.5529999999997,
            "bootup-time": 544.2519999999998,
            "network-requests": 12,
            "network-rtt": 0.086,
            "network-server-latency": 571.3829999999999,
            "main-thread-tasks": 15,
            "metrics": 2903.699,
            "total-byte-weight": 144889,
            "render-blocking-resources": 721,
            "dom-size": 31
        },
        "time": 1575914966397
    },
    {
        "date": "2019-12-09",
        "datetime": "2019-12-09T18:17:51.535Z",
        "package": "@ionic/angular@4.11.5",
        "audits": {
            "scriptEvaluation": 393.35999999999933,
            "other": 96.86899999999997,
            "scriptParseCompile": 57.07499999999999,
            "styleLayout": 17.561,
            "paintCompositeRender": 8.657999999999998,
            "parseHTML": 7.920999999999999,
            "garbageCollection": 2.518,
            "first-contentful-paint": 2834.916,
            "first-meaningful-paint": 2834.916,
            "load-fast-enough-for-pwa": 2834.916,
            "speed-index": 2840,
            "estimated-input-latency": 16,
            "max-potential-fid": 16,
            "time-to-first-byte": 563.8480000000001,
            "first-cpu-idle": 2834.916,
            "interactive": 2834.916,
            "mainthread-work-breakdown": 583.9619999999994,
            "bootup-time": 336.4819999999997,
            "network-requests": 12,
            "network-rtt": 0.077,
            "network-server-latency": 571.8059999999999,
            "main-thread-tasks": 16,
            "metrics": 2834.916,
            "total-byte-weight": 144889,
            "render-blocking-resources": 722,
            "dom-size": 31
        },
        "time": 1575915471535
    }
]