[
    {
        "date": "2019-12-13",
        "datetime": "2019-12-13T06:06:32.015Z",
        "package": "@ionic/angular@4.11.7",
        "audits": {
            "scriptEvaluation": 731.9359999999883,
            "other": 181.23600000000027,
            "styleLayout": 112.20800000000001,
            "scriptParseCompile": 89.436,
            "paintCompositeRender": 28.008000000000017,
            "parseHTML": 16.179999999999996,
            "garbageCollection": 7.036,
            "first-contentful-paint": 1854.8274999999999,
            "first-meaningful-paint": 1854.8274999999999,
            "load-fast-enough-for-pwa": 2587.6549999999997,
            "speed-index": 1854.8274999999999,
            "estimated-input-latency": 12.8,
            "total-blocking-time": 99.99999999999989,
            "max-potential-fid": 176,
            "time-to-first-byte": 13.476,
            "first-cpu-idle": 2282.66,
            "interactive": 2587.6549999999997,
            "mainthread-work-breakdown": 1166.0399999999888,
            "bootup-time": 606.9400000000003,
            "network-requests": 28,
            "network-rtt": 0.1859999999999995,
            "network-server-latency": 1.6650000000000005,
            "main-thread-tasks": 13,
            "metrics": 2587.6549999999997,
            "total-byte-weight": 172004,
            "render-blocking-resources": 152,
            "dom-size": 136
        },
        "time": 1576217192015
    },
    {
        "date": "2019-12-13",
        "datetime": "2019-12-13T06:35:37.294Z",
        "package": "@ionic/angular@4.11.7",
        "audits": {
            "scriptEvaluation": 632.6319999999953,
            "other": 152.51200000000009,
            "scriptParseCompile": 76.96000000000005,
            "styleLayout": 67.284,
            "paintCompositeRender": 20.956000000000003,
            "parseHTML": 11.663999999999987,
            "garbageCollection": 5.236,
            "first-contentful-paint": 1824.2525,
            "first-meaningful-paint": 1824.2525,
            "load-fast-enough-for-pwa": 2567.5050000000006,
            "speed-index": 1824.2525,
            "estimated-input-latency": 12.8,
            "total-blocking-time": 77,
            "max-potential-fid": 159,
            "time-to-first-byte": 9.02,
            "first-cpu-idle": 2263.86,
            "interactive": 2567.5050000000006,
            "mainthread-work-breakdown": 967.2439999999954,
            "bootup-time": 550.2800000000009,
            "network-requests": 28,
            "network-rtt": 0.043999999999999984,
            "network-server-latency": 1.2149999999999999,
            "main-thread-tasks": 8,
            "metrics": 2567.5050000000006,
            "total-byte-weight": 172004,
            "render-blocking-resources": 151,
            "dom-size": 136
        },
        "time": 1576218937294
    },
    {
        "date": "2019-12-13",
        "datetime": "2019-12-13T10:05:50.994Z",
        "package": "@ionic/angular@4.11.7",
        "audits": {
            "scriptEvaluation": 810.579999999994,
            "other": 185.49200000000013,
            "scriptParseCompile": 97.64399999999999,
            "styleLayout": 86.80799999999999,
            "paintCompositeRender": 23.436000000000007,
            "parseHTML": 13.147999999999996,
            "garbageCollection": 6.38,
            "first-contentful-paint": 1879.5965,
            "first-meaningful-paint": 1879.5965,
            "load-fast-enough-for-pwa": 2777.7920000000004,
            "speed-index": 1879.5965,
            "estimated-input-latency": 12.8,
            "total-blocking-time": 139.4999999999999,
            "max-potential-fid": 215,
            "time-to-first-byte": 9.876000000000001,
            "first-cpu-idle": 2321.396,
            "interactive": 2777.7920000000004,
            "mainthread-work-breakdown": 1223.4879999999941,
            "bootup-time": 695.7360000000009,
            "network-requests": 28,
            "network-rtt": 0.067,
            "network-server-latency": 1.599,
            "main-thread-tasks": 13,
            "metrics": 2777.7920000000004,
            "total-byte-weight": 172004,
            "render-blocking-resources": 152,
            "dom-size": 136
        },
        "time": 1576231550994
    },
    {
        "date": "2019-12-13",
        "datetime": "2019-12-13T10:35:09.712Z",
        "package": "@ionic/angular@4.11.7",
        "audits": {
            "scriptEvaluation": 574.4319999999996,
            "other": 166.45600000000027,
            "styleLayout": 100.76400000000001,
            "scriptParseCompile": 63.940000000000005,
            "paintCompositeRender": 32.74799999999999,
            "parseHTML": 14.088000000000001,
            "garbageCollection": 5.86,
            "first-contentful-paint": 1826.6399999999999,
            "first-meaningful-paint": 1826.6399999999999,
            "load-fast-enough-for-pwa": 2539.2799999999997,
            "speed-index": 1826.6399999999999,
            "estimated-input-latency": 12.8,
            "total-blocking-time": 65,
            "max-potential-fid": 132,
            "time-to-first-byte": 9.172,
            "first-cpu-idle": 2236.16,
            "interactive": 2539.2799999999997,
            "mainthread-work-breakdown": 958.2879999999998,
            "bootup-time": 424.91600000000034,
            "network-requests": 28,
            "network-rtt": 0.051000000000000045,
            "network-server-latency": 1.04,
            "main-thread-tasks": 12,
            "metrics": 2539.2799999999997,
            "total-byte-weight": 172004,
            "render-blocking-resources": 151,
            "dom-size": 136
        },
        "time": 1576233309712
    },
    {
        "date": "2019-12-13",
        "datetime": "2019-12-13T20:05:41.299Z",
        "package": "@ionic/angular@4.11.7",
        "audits": {
            "scriptEvaluation": 533.4520000000008,
            "other": 134.78000000000014,
            "styleLayout": 80.39600000000002,
            "scriptParseCompile": 62.28799999999998,
            "paintCompositeRender": 24.591999999999995,
            "parseHTML": 9.427999999999988,
            "garbageCollection": 5.776,
            "first-contentful-paint": 1819.5384999999999,
            "first-meaningful-paint": 1819.5384999999999,
            "load-fast-enough-for-pwa": 2462.5715,
            "speed-index": 1819.5384999999999,
            "estimated-input-latency": 12.8,
            "total-blocking-time": 61,
            "max-potential-fid": 131,
            "time-to-first-byte": 9.13,
            "first-cpu-idle": 2235.044,
            "interactive": 2462.5715,
            "mainthread-work-breakdown": 850.712000000001,
            "bootup-time": 391.6280000000006,
            "network-requests": 28,
            "network-rtt": 0.046999999999999986,
            "network-server-latency": 1.0110000000000001,
            "main-thread-tasks": 10,
            "metrics": 2462.5715,
            "total-byte-weight": 172004,
            "render-blocking-resources": 151,
            "dom-size": 136
        },
        "time": 1576267541299
    },
    {
        "date": "2019-12-13",
        "datetime": "2019-12-13T20:35:12.338Z",
        "package": "@ionic/angular@4.11.7",
        "audits": {
            "scriptEvaluation": 694.8879999999924,
            "other": 191.77600000000024,
            "styleLayout": 98.52000000000001,
            "scriptParseCompile": 66.44800000000001,
            "paintCompositeRender": 26.17600000000001,
            "parseHTML": 12.244000000000002,
            "garbageCollection": 5.94,
            "first-contentful-paint": 1864.626,
            "first-meaningful-paint": 1864.626,
            "load-fast-enough-for-pwa": 2588.2520000000004,
            "speed-index": 1864.626,
            "estimated-input-latency": 12.8,
            "total-blocking-time": 108.50000000000011,
            "max-potential-fid": 181,
            "time-to-first-byte": 9.671,
            "first-cpu-idle": 2285.1440000000002,
            "interactive": 2588.2520000000004,
            "mainthread-work-breakdown": 1095.9919999999927,
            "bootup-time": 524.2800000000008,
            "network-requests": 28,
            "network-rtt": 0.045999999999999985,
            "network-server-latency": 1.0359999999999998,
            "main-thread-tasks": 15,
            "metrics": 2588.2520000000004,
            "total-byte-weight": 172004,
            "render-blocking-resources": 151,
            "dom-size": 136
        },
        "time": 1576269312338
    },
    {
        "date": "2019-12-14",
        "datetime": "2019-12-14T06:05:22.236Z",
        "package": "@ionic/angular@4.11.7",
        "audits": {
            "scriptEvaluation": 562.416000000001,
            "other": 156.1000000000002,
            "styleLayout": 91.11200000000001,
            "scriptParseCompile": 65.49599999999997,
            "paintCompositeRender": 23.18400000000001,
            "parseHTML": 19.152,
            "garbageCollection": 5.732,
            "first-contentful-paint": 1825.871,
            "first-meaningful-paint": 1825.871,
            "load-fast-enough-for-pwa": 2538.7419999999993,
            "speed-index": 1825.871,
            "estimated-input-latency": 12.8,
            "total-blocking-time": 63.999999999999886,
            "max-potential-fid": 131,
            "time-to-first-byte": 9.334999999999999,
            "first-cpu-idle": 2235.424,
            "interactive": 2538.7419999999993,
            "mainthread-work-breakdown": 923.1920000000011,
            "bootup-time": 428.4960000000005,
            "network-requests": 28,
            "network-rtt": 0.046999999999999986,
            "network-server-latency": 1.106,
            "main-thread-tasks": 10,
            "metrics": 2538.7419999999993,
            "total-byte-weight": 172004,
            "render-blocking-resources": 151,
            "dom-size": 136
        },
        "time": 1576303522236
    }
]